odoo/addons/helm/LICENSE
odoo/addons/helm/README.rst
odoo/addons/helm/__init__.py
odoo/addons/helm/__manifest__.py
odoo/addons/helm/data/data.xml
odoo/addons/helm/demo/demo.xml
odoo/addons/helm/images/screen.png
odoo/addons/helm/models/__init__.py
odoo/addons/helm/models/helm_chart.py
odoo/addons/helm/models/helm_chart_secret.py
odoo/addons/helm/models/helm_chart_secret_data.py
odoo/addons/helm/models/helm_chart_value.py
odoo/addons/helm/models/helm_release.py
odoo/addons/helm/models/helm_repo.py
odoo/addons/helm/models/ir_actions_client.py
odoo/addons/helm/models/product_template.py
odoo/addons/helm/models/res_partner.py
odoo/addons/helm/security/ir.model.access.csv
odoo/addons/helm/security/security.xml
odoo/addons/helm/static/description/icon.png
odoo/addons/helm/static/description/icon.svg
odoo/addons/helm/static/description/index.html
odoo/addons/helm/tests/TEST_INSTRUCTIONS.rst
odoo/addons/helm/views/helm_chart_secret_views.xml
odoo/addons/helm/views/helm_chart_value_views.xml
odoo/addons/helm/views/helm_chart_views.xml
odoo/addons/helm/views/helm_release_views.xml
odoo/addons/helm/views/helm_repo_views.xml
odoo/addons/helm/views/product_template.xml
odoo/addons/helm/views/res_partner_views.xml
odoo/addons/helm/wizards/__init__.py
odoo/addons/helm/wizards/helm_chart_install.py
odoo/addons/helm/wizards/helm_chart_install.xml
odoo_addon_helm-18.0.1.0.0.dist-info/METADATA
odoo_addon_helm-18.0.1.0.0.dist-info/WHEEL
odoo_addon_helm-18.0.1.0.0.dist-info/top_level.txt
odoo_addon_helm-18.0.1.0.0.dist-info/RECORD
